{"data": {"raw": {"reviews-subset_most-commonly-reviewed_csv": "data/subset/amazon-reviews-subset-grocery-most-common-products.csv.gz", "reviews-subset_selected-brand_csv": "data/subset/amazon-reviews-subset-brand-Miracle Noodle.csv.gz", "metadata_csv": "data/subset/amazon-metadata-subset-grocery-most-common-products.csv.gz"}, "processed": {"processed-reviews-spacy_json": "data/processed/processed-reviews.json", "processed-reviews-spacy_joblib": "data/processed/processed-reviews.joblib"}, "app": {}, "ml-nlp": {"reviews-with-target_json": "data/modeling/processed-nlp-reviews-for-ml.json", "train_joblib": "data/modeling/training-data.joblib", "test_joblib": "Data-NLP/modeling/testing-data.joblib"}, "ml-tabular": {"reviews-with-ml-target_json": "Data/modeling/processed-movie-data-for-ml.json", "train_joblib": "data/modeling/training-data.joblib", "test_joblib": "data/modeling/testing-data.joblib"}, "nn": {"train_dir": "data/modeling/training-data-tf/", "test_dir": "data/modeling/testing-data-tf/"}}, "images": {"banner": "images/app-banner.png"}, "metadata": {"target_lookup": "data/metadata/target-lookup.json"}, "eda": {"wordclouds-by-group_png": "images/wordclouds-compare-groups.png", "scattertext-by-group_html": "app-assets/scattertext-roi.html"}, "models": {"ml": {"bayes_joblib": "models/bayes-clf.joblib", "random_forest_joblib": "models/random-forest.joblib", "logreg_joblib": "models/log-reg.joblib"}, "nn": {"LSTM_dir": "models/keras/lstm/", "GRU_dir": "models/keras/gru/", "Attention_model_dir": "models/keras/attn/"}}}